MANIFEST.in
README.rst
setup.cfg
setup.py
tw2/__init__.py
tw2.jqplugins.fullcalendar.egg-info/PKG-INFO
tw2.jqplugins.fullcalendar.egg-info/SOURCES.txt
tw2.jqplugins.fullcalendar.egg-info/dependency_links.txt
tw2.jqplugins.fullcalendar.egg-info/entry_points.txt
tw2.jqplugins.fullcalendar.egg-info/namespace_packages.txt
tw2.jqplugins.fullcalendar.egg-info/not-zip-safe
tw2.jqplugins.fullcalendar.egg-info/requires.txt
tw2.jqplugins.fullcalendar.egg-info/top_level.txt
tw2/jqplugins/__init__.py
tw2/jqplugins/fullcalendar/__init__.py
tw2/jqplugins/fullcalendar/base.py
tw2/jqplugins/fullcalendar/samples.py
tw2/jqplugins/fullcalendar/widgets.py
tw2/jqplugins/fullcalendar/static/GPL-LICENSE.txt
tw2/jqplugins/fullcalendar/static/MIT-LICENSE.txt
tw2/jqplugins/fullcalendar/static/css/fullcalendar.css
tw2/jqplugins/fullcalendar/static/css/fullcalendar.print.css
tw2/jqplugins/fullcalendar/static/js/fullcalendar.js
tw2/jqplugins/fullcalendar/static/js/fullcalendar.min.js
tw2/jqplugins/fullcalendar/static/js/gcal.js
tw2/jqplugins/fullcalendar/templates/__init__.py
tw2/jqplugins/fullcalendar/templates/fullcalendar.mak
tw2/jqplugins/fullcalendar/templates/generic_jq_ui_js.mak