Metadata-Version: 1.0
Name: tw2.jqplugins.fullcalendar
Version: 2.0.1
Summary: toscawidgets2 wrapper for the FullCalendar jQuery plugin
Home-page: https://github.com/RobertSudwarts/tw2.jqplugins.fullcalendar
Author: Robert Sudwarts
Author-email: robert.sudwarts@gmail.com
License: MIT
Keywords: tocsawidget2 widgets
Platform: UNKNOWN
Classifier: Development Status :: 3 - Alpha
Classifier: Environment :: Web Environment
Classifier: Environment :: Web Environment :: ToscaWidgets
Classifier: Topic :: Software Development :: Libraries :: Python Modules
Classifier: Topic :: Software Development :: Widget Sets
Classifier: Intended Audience :: Developers
Classifier: Operating System :: OS Independent
Classifier: Programming Language :: Python
